neon_phal_plugin_system/__init__.py
neon_phal_plugin_system/version.py
neon_phal_plugin_system/ui/Reboot.qml
neon_phal_plugin_system/ui/Restart.qml
neon_phal_plugin_system/ui/Shutdown.qml
neon_phal_plugin_system/ui/Status.qml
neon_phal_plugin_system/ui/animations/loading.json
neon_phal_plugin_system/ui/animations/status-fail.json
neon_phal_plugin_system/ui/animations/status-success.json
neon_phal_plugin_system-1.3.0.dist-info/LICENSE
neon_phal_plugin_system-1.3.0.dist-info/METADATA
neon_phal_plugin_system-1.3.0.dist-info/WHEEL
neon_phal_plugin_system-1.3.0.dist-info/entry_points.txt
neon_phal_plugin_system-1.3.0.dist-info/top_level.txt
neon_phal_plugin_system-1.3.0.dist-info/zip-safe
neon_phal_plugin_system-1.3.0.dist-info/RECORD
